{
  "data": {
    "perfil": [
      {
        "_id": "01JJSH5BE6TJH7FAJD30MDE0WM",
        "_apelido": "1",
        "_email": "1",
        "_foto": "😀",
        "_senha": "1",
        "_stats": true,
        "_amigos": [],
        "_publicacoes": [],
        "_solicitacoesAmizade": []
      },
      {
        "_id": "01JJSJ32ZCFTV2SDDHYDRTSTGQ",
        "_apelido": "2",
        "_email": "2",
        "_foto": "😃",
        "_senha": "2",
        "_stats": true,
        "_amigos": [],
        "_publicacoes": [],
        "_solicitacoesAmizade": []
      },
      {
        "_id": "01JJSJN4WJ1259A9CZCR1VARHY",
        "_apelido": "3",
        "_email": "3",
        "_foto": "🙂",
        "_senha": "3",
        "_stats": true,
        "_amigos": [],
        "_publicacoes": [],
        "_solicitacoesAmizade": []
      },
      {
        "_id": "01JJT5FW6PJJ4S0WQK7HH7J5P4",
        "_apelido": "4",
        "_email": "4",
        "_foto": "😃",
        "_senha": "4",
        "_stats": true,
        "_amigos": [],
        "_publicacoes": [],
        "_solicitacoesAmizade": []
      },
      {
        "_id": "01JJTC9AH49FY1Z42FTW248YBG",
        "_apelido": "5",
        "_email": "5",
        "_foto": "🫠",
        "_senha": "5",
        "_stats": true,
        "_amigos": [],
        "_publicacoes": [],
        "_solicitacoesAmizade": []
      }
    ],
    "publicacao": [
      {
        "id": 1,
        "conteudo": "Primeira publicacao",
        "dataHora": "2024-01-01",
        "perfilAssociado": "apelido1"
      }
    ]
  }
}